LICENSE
MANIFEST.in
README.md
README.rst
setup.cfg
setup.py
debug_toolbar_multilang/__init__.py
debug_toolbar_multilang/views.py
debug_toolbar_multilang/locale/de/LC_MESSAGES/django.mo
debug_toolbar_multilang/locale/de/LC_MESSAGES/django.po
debug_toolbar_multilang/panels/__init__.py
debug_toolbar_multilang/panels/multilang.py
debug_toolbar_multilang/templates/debug_toolbar_multilang/multilang.html
django_debug_toolbar_multilang.egg-info/PKG-INFO
django_debug_toolbar_multilang.egg-info/SOURCES.txt
django_debug_toolbar_multilang.egg-info/dependency_links.txt
django_debug_toolbar_multilang.egg-info/not-zip-safe
django_debug_toolbar_multilang.egg-info/requires.txt
django_debug_toolbar_multilang.egg-info/top_level.txt