Metadata-Version: 1.1
Name: django-debug-toolbar-multilang
Version: 1.0.1
Summary: Language panel for django-debug-toolbar
Home-page: http://github.com/matt3o12/django-debug-toolbar-multilang
Author: Matteo Kloiber
Author-email: info@matt3o12.de
License: MIT
Platform: UNKNOWN
Classifier: Framework :: Django
Classifier: Intended Audience :: Developers
Classifier: License :: OSI Approved :: MIT License
Classifier: Natural Language :: English
Classifier: Natural Language :: German
Classifier: Operating System :: OS Independent
Classifier: Programming Language :: Python :: 2.7
Classifier: Programming Language :: Python :: 3.2
Classifier: Programming Language :: Python :: 3.3
Classifier: Programming Language :: Python :: 3.4
